L2Boost/OrthBoost.py
L2Boost/__init__.py
L2Boost-0.0.1.dist-info/METADATA
L2Boost-0.0.1.dist-info/WHEEL
L2Boost-0.0.1.dist-info/top_level.txt
L2Boost-0.0.1.dist-info/RECORD
